{"session_file":"8801616746600","phone":"8801616746600","password":"s2ZJX","register_time":1663949070,"app_id":"3424469","app_hash":"fb4d11fe9bd453ea509f330789417029","sdk":"9.0.5 (73152)","app_version":"0.6ph5.8cH.0241-nJjsxbs-u7g (110)","device":"s4C pzV","last_check_time":1663949070,"avatar":null,"first_name":"\u041c\u0430\u0439\u044f","last_name":"\u0415\u0440\u043c\u0430\u043a\u043e\u0432\u0430","username":"carlene1919","sex":0,"lang_pack":"bq","system_lang_pack":"ae_um","proxy":[3,"isp2.hydraproxy.com",9989,true,"tagi13062ilkq30219","GboY4Ctua79RWtwd_country-India"],"ipv6":false}