{"session_file":"8801534352889","phone":"8801534352889","password":"U52vt9wOiAF","register_time":1663952604,"app_id":"3895673","app_hash":"324f043dec216cbb9d25fa4db1b9b648","sdk":"0.7.8.8 (4838)","app_version":"Clr (8.6)","device":"DWIfSo XWJpe MTx (Ch519L)raHq","last_check_time":1663952604,"avatar":null,"first_name":"\u0412\u0430\u0441\u0438\u043b\u0438\u0441\u0430","last_name":"\u041d\u0430\u0432\u0430\u043b\u044c\u043d\u0430\u044f","username":"AmourPourer","sex":0,"lang_pack":"mp","system_lang_pack":"tm_vj","proxy":[3,"isp2.hydraproxy.com",9989,true,"tagi13062ilkq30219","GboY4Ctua79RWtwd_country-India"],"ipv6":false}