{"session_file":"8801580575572","phone":"8801580575572","password":"t4XJDp24g","register_time":1663951825,"app_id":"3638243","app_hash":"efce2718fda00a1b1987ba6d6f738d1b","sdk":"0.9.9.3 (0745)","app_version":"0.7.8.1.5 (85)","device":"UM YXFE 2","last_check_time":1663951825,"avatar":null,"first_name":"\u041d\u043e\u043d\u043d\u0430","last_name":"\u0428\u0443\u043c\u0435\u0439\u043a\u043e\u0432\u0430","username":"zbkdlU","sex":0,"lang_pack":"xb","system_lang_pack":"iz_pc","proxy":[3,"isp2.hydraproxy.com",9989,true,"tagi13062ilkq30219","GboY4Ctua79RWtwd_country-India"],"ipv6":false}